{"sources": {"/root/mfem/examples/685.cpp": {"": {"functions": {"main": {"start_line": 7, "execution_count": 1}}, "branches": {}, "lines": {"7": 1, "13": 2, "17": 1, "18": 1, "21": 1, "27": 21, "29": 20, "31": 1, "32": 1, "33": 1, "36": 1, "37": 1, "40": 1}}}, "/root/mfem/general/mem_alloc.hpp": {"": {"functions": {"_ZN4mfem5StackIPNS_11TetrahedronELi1024EE5ClearEv": {"start_line": 83, "execution_count": 3}, "_ZN4mfem8MemAllocINS_11TetrahedronELi1024EE5ClearEv": {"start_line": 170, "execution_count": 2}}, "branches": {}, "lines": {"42": 1, "83": 3, "86": 3, "88": 0, "89": 0, "91": 3, "93": 0, "94": 0, "96": 3, "97": 3, "98": 3, "122": 0, "142": 1, "170": 2, "173": 2, "175": 0, "176": 0, "177": 0, "179": 2, "180": 2, "181": 2}}}, "/root/mfem/fem/eltrans.hpp": {"": {"functions": {"_ZN4mfem21ElementTransformationD0Ev": {"start_line": 104, "execution_count": 0}, "_ZN4mfem21ElementTransformationD2Ev": {"start_line": 104, "execution_count": 6}, "_ZN4mfem27IsoparametricTransformationD0Ev": {"start_line": 333, "execution_count": 0}, "_ZN4mfem27IsoparametricTransformationD2Ev": {"start_line": 333, "execution_count": 6}}, "branches": {}, "lines": {"104": 6, "313": 2, "333": 12, "336": 1, "344": 1}}}, "/root/mfem/mesh/mesh.hpp": {"": {"functions": {"_ZN4mfem4MeshD0Ev": {"start_line": 1238, "execution_count": 0}, "_ZN4mfem4MeshD2Ev": {"start_line": 1238, "execution_count": 1}}, "branches": {}, "lines": {"656": 1, "1238": 3}}}, "/root/mfem/general/array.hpp": {"": {"functions": {}, "branches": {}, "lines": {"73": 1, "74": 1, "94": 4, "605": 21}}}, "/root/mfem/mesh/ncmesh.hpp": {"": {"functions": {}, "branches": {}, "lines": {"55": 1}}}, "/root/mfem/linalg/vector.hpp": {"": {"functions": {"_ZN4mfem6VectorD0Ev": {"start_line": 388, "execution_count": 20}, "_ZN4mfem6VectorD2Ev": {"start_line": 388, "execution_count": 0}}, "branches": {}, "lines": {"388": 46, "390": 26, "392": 20, "394": 20}}}, "/root/mfem/mesh/tetrahedron.hpp": {"": {"functions": {"_ZN4mfem11TetrahedronD0Ev": {"start_line": 110, "execution_count": 0}, "_ZN4mfem11TetrahedronD2Ev": {"start_line": 110, "execution_count": 0}}, "branches": {}, "lines": {"110": 0}}}, "/root/mfem/linalg/densemat.hpp": {"": {"functions": {"_ZN4mfem11DenseTensorD2Ev": {"start_line": 744, "execution_count": 0}}, "branches": {}, "lines": {"744": 0, "745": 0, "746": 0, "747": 0}}}}}